LICENSE
MANIFEST.in
README.md
setup.cfg
setup.py
Ctl/VERSION
Ctl/requirements-docs.txt
Ctl/requirements-test.txt
Ctl/requirements.txt
cfu.egg-info/PKG-INFO
cfu.egg-info/SOURCES.txt
cfu.egg-info/dependency_links.txt
cfu.egg-info/requires.txt
cfu.egg-info/top_level.txt
cfu.egg-info/zip-safe
confu/__init__.py
confu/cli.py
confu/config.py
confu/exceptions.py
confu/generator.py
confu/util.py
confu/schema/__init__.py
confu/schema/core.py
confu/schema/inet.py
tests/__init__.py
tests/conftest.py
tests/schemas.py
tests/test_argparse.py
tests/test_attributes.py
tests/test_click.py
tests/test_config.py
tests/test_generators.py
tests/test_schema.py
tests/test_util.py
tests/test_validation.py