Metadata-Version: 1.1
Name: cfu
Version: 1.1.2
Summary: Configuration file validation and generation
Home-page: https://github.com/20c/confu
Author: 20C
Author-email: code@20c.com
License: LICENSE.txt
Download-URL: https://github.com/20c/confu/1.1.2
Platform: UNKNOWN
Classifier: Development Status :: 4 - Beta
Classifier: License :: OSI Approved :: Apache Software License
Classifier: Programming Language :: Python :: 2.7
Classifier: Programming Language :: Python :: 3.4
Classifier: Programming Language :: Python :: 3.5
Classifier: Programming Language :: Python :: 3.6
